ascend_io_test/framework/__init__.py
ascend_io_test/framework/ascend_pyspark_transform.py
ascend_io_test/framework/ascend_python_bytestream_read_connector.py
ascend_io_test/framework/ascend_python_read_connector.py
ascend_io_test-0.9.7.dist-info/LICENSE
ascend_io_test-0.9.7.dist-info/METADATA
ascend_io_test-0.9.7.dist-info/WHEEL
ascend_io_test-0.9.7.dist-info/entry_points.txt
ascend_io_test-0.9.7.dist-info/RECORD
