Metadata-Version: 2.1
Name: ascend-io-test
Version: 0.9.7
Summary: The Ascend Python Test Framework
Home-page: https://www.ascend.io
License: Apache-2.0
Keywords: ascend,pipeline,data,automation,platform
Author: Ascend.io Engineering
Author-email: support@ascend.io
Maintainer: Ascend.io Engineering
Maintainer-email: support@ascend.io
Requires-Python: >=3.9,<4.0
Classifier: Intended Audience :: Developers
Classifier: License :: OSI Approved :: Apache Software License
Classifier: Programming Language :: Python :: 3
Classifier: Programming Language :: Python :: 3.9
Classifier: Programming Language :: Python :: 3.10
Classifier: Programming Language :: Python :: 3.11
Classifier: Programming Language :: Python :: 3 :: Only
Classifier: Topic :: Software Development :: Build Tools
Classifier: Topic :: Software Development :: Libraries :: Python Modules
Requires-Dist: pandas (>=2.1.0,<3.0.0)
Requires-Dist: pyspark (>=3.3.1,<4.0.0)
Requires-Dist: pytest (>=7.2.1,<8.0.0)
Requires-Dist: pytest-mock (>=3.10.0,<4.0.0)
Project-URL: Ascend.io, https://www.ascend.io
Project-URL: Ascend Developer Hub, https://developer.ascend.io
Project-URL: Documentation, https://developer.ascend.io
